msfr/__init__.py
msfr/core.py
msfr/imaginary.py
msfr-1.1.0.dist-info/licenses/LICENSE
msfr-1.1.0.dist-info/METADATA
msfr-1.1.0.dist-info/WHEEL
msfr-1.1.0.dist-info/top_level.txt
msfr-1.1.0.dist-info/RECORD
