Metadata-Version: 2.4
Name: MSFR
Version: 1.1.0
Summary: Python library for multi-seasonal time series regression with Fourier features and smoothing
Author-email: rrayy <taejunham1@gmail.com>, tatatommy6 <tatatommy6@naver.com>
License-Expression: Apache-2.0
Project-URL: Homepage, https://github.com/tatatommy6/multi-seasonal-fourier-regression
Project-URL: Repository, https://github.com/tatatommy6/multi-seasonal-fourier-regression
Project-URL: Issues, https://github.com/tatatommy6/multi-seasonal-fourier-regression/issues
Requires-Python: >=3.11
License-File: LICENSE
Requires-Dist: torch==2.8.0
Dynamic: license-file
